Metadata-Version: 2.1
Name: twitterplus
Version: 2.0
Summary: A simple module to work with the twitter api.
Home-page: https://github.com/anthony16t/twitterplus
Author: anthony16t
Author-email: info@anthony16t.com
License: MIT
Keywords: twitter,api,developer
Platform: UNKNOWN
Classifier: Development Status :: 4 - Beta
Classifier: Intended Audience :: Education
Classifier: License :: OSI Approved :: MIT License
Classifier: Operating System :: Unix
Classifier: Operating System :: MacOS :: MacOS X
Classifier: Operating System :: Microsoft :: Windows
Classifier: Programming Language :: Python :: 3
License-File: LICENCE.txt
